freeproxy/__init__.py
freeproxy/_utils.py
freeproxy/_version.py
freeproxy/async_client.py
freeproxy/client.py
freeproxy/exceptions.py
freeproxy/models.py
freeproxy_python-1.0.1.dist-info/licenses/LICENSE
freeproxy_python-1.0.1.dist-info/METADATA
freeproxy_python-1.0.1.dist-info/WHEEL
freeproxy_python-1.0.1.dist-info/top_level.txt
freeproxy_python-1.0.1.dist-info/RECORD
