Metadata-Version: 2.4
Name: freeproxy-python
Version: 1.0.1
Summary: Python client for the FreeProxy API
Author: gfpcom
License: MIT
Requires-Python: >=3.9
License-File: LICENSE
Requires-Dist: httpx>=0.23
Provides-Extra: dev
Requires-Dist: pytest>=7.0; extra == "dev"
Requires-Dist: respx>=0.19; extra == "dev"
Requires-Dist: pytest-asyncio>=0.20; extra == "dev"
Dynamic: license-file
